discord/ext/songbird/__init__.py
discord/ext/songbird/__init__.pyi
discord/ext/songbird/client.py
discord/ext/songbird/native.cpython-314-aarch64-linux-gnu.so
discord/ext/songbird/native/__init__.pyi
discord/ext/songbird/native/error/__init__.pyi
discord/ext/songbird/native/model/__init__.pyi
discord/ext/songbird/native/player/__init__.pyi
discord/ext/songbird/native/receive/__init__.pyi
discord/ext/songbird/py.typed
discord_ext_songbird-0.4.3.dist-info/METADATA
discord_ext_songbird-0.4.3.dist-info/WHEEL
discord_ext_songbird-0.4.3.dist-info/licenses/LICENSE
discord_ext_songbird-0.4.3.dist-info/RECORD
