Metadata-Version: 2.4
Name: discord-ext-songbird
Version: 0.4.3
Classifier: Programming Language :: Rust
Classifier: Programming Language :: Python :: Implementation :: CPython
Classifier: Programming Language :: Python :: Implementation :: PyPy
Classifier: Development Status :: 4 - Beta
Classifier: License :: OSI Approved :: MIT License
Classifier: Programming Language :: Python :: 3.13
Classifier: Programming Language :: Python :: 3.14
Requires-Dist: audioop-lts ; python_full_version >= '3.13'
Requires-Dist: typing-extensions>=4.15.0
Requires-Dist: ty>=0.0.8
Requires-Dist: pyarrow>=22.0.0
Requires-Dist: arro3-core>=0.6.5
Requires-Dist: arro3-io>=0.6.5
Requires-Dist: arro3-compute>=0.6.5
License-File: LICENSE
Summary: Library to replace the voice backend of discord.py with Songbird.
Author: Sumito Izumita <mail@smdr.io>
Author-email: Sumito Izumita <mail@smdr.io>
License: MIT
Requires-Python: >=3.13
